spectrographic
