Metadata-Version: 2.1
Name: spectrographic
Version: 0.9.3
Summary: Draw Images into Spectrograms
Home-page: https://github.com/LeviBorodenko/spectrographic
Author: Levi Borodenko
Author-email: Levi.borodenko@gmail.com
License: mit
Platform: any
Classifier: Development Status :: 4 - Beta
Classifier: Programming Language :: Python
Provides-Extra: testing
